cvnum/LICENSE.txt
cvnum/README.md
cvnum/__init__.py
cvnum/config/__init__.py
cvnum/config/digit.py
cvnum/config/textify/__init__.py
cvnum/config/textify/langint.py
cvnum/convert/__init__.py
cvnum/convert/integer/__init__.py
cvnum/convert/integer/base2base.py
cvnum/convert/integer/base2int.py
cvnum/convert/integer/int2base.py
cvnum/convert/integer/intconv.py
cvnum/convert/natural/__init__.py
cvnum/convert/natural/base2base.py
cvnum/convert/natural/base2nat.py
cvnum/convert/natural/nat2base.py
cvnum/convert/natural/natconv.py
cvnum/core/__init__.py
cvnum/core/var2int.py
cvnum/textify/__init__.py
cvnum/textify/automata.py
cvnum/textify/integer.py
cvnum-0.0.0.dist-info/WHEEL
cvnum-0.0.0.dist-info/METADATA
cvnum-0.0.0.dist-info/RECORD
