Metadata-Version: 2.1
Name: cvnum
Version: 0.0.0
Summary: A tool to convert mathematical numbers in several formats.
Home-page: https://github.com/math-tools/math-objects/tree/main/cvnum
License: GNU License Version 3
Author: Christophe BAL
Maintainer: Christophe BAL
Requires-Python: >=3.8,<4.0
Classifier: License :: Other/Proprietary License
Classifier: Programming Language :: Python :: 3
Classifier: Programming Language :: Python :: 3.8
Classifier: Programming Language :: Python :: 3.9
Project-URL: Repository, https://github.com/math-tools/math-objects/tree/main/cvnum
